dbtk_dnabert-1.2.2.dist-info/licenses/LICENSE
dnabert/__init__.py
dnabert/datamodules.py
dnabert/models.py
dnabert/tokenizers.py
dbtk_dnabert-1.2.2.dist-info/METADATA
dbtk_dnabert-1.2.2.dist-info/WHEEL
dbtk_dnabert-1.2.2.dist-info/top_level.txt
dbtk_dnabert-1.2.2.dist-info/RECORD
