Metadata-Version: 2.4
Name: dbtk-dnabert
Version: 1.2.2
Summary: A general DNABERT implementation using the deepbio-toolkit.
Author-email: "David W. Ludwig II" <davidludwigii@gmail.com>
License: MIT License
Project-URL: Homepage, https://github.com/DLii-Research/dbtk-dnabert
Project-URL: Bug Tracker, https://github.com/DLii-Research/dbtk-dnabert/issues
Requires-Python: >=3.8
License-File: LICENSE
Requires-Dist: deepbio-toolkit>=0.4.3
Requires-Dist: lightning
Dynamic: license-file
